{"kind":"identitytoolkit#DownloadAccountResponse","users":[{"localId":"FO4MzGK0RxBewIK2v3vhlBIaourz","createdAt":"1730837075989","lastLoginAt":"1730837095753","displayName":"Ramy Hatimy","photoUrl":"https://lh3.googleusercontent.com/a/ACg8ocJPGftnRmQ-9s-wnGLGNfMbm5FtDc2es3qpiEXKQcxwdejJgA=s96-c","providerUserInfo":[{"providerId":"google.com","rawId":"111595754218918728280","federatedId":"111595754218918728280","displayName":"Ramy Hatimy","photoUrl":"https://lh3.googleusercontent.com/a/ACg8ocJPGftnRmQ-9s-wnGLGNfMbm5FtDc2es3qpiEXKQcxwdejJgA=s96-c","email":"hatimyramy@gmail.com"}],"validSince":"1733634018","email":"hatimyramy@gmail.com","emailVerified":true,"disabled":false},{"localId":"knD7kyiXilYhNQTXBqHRs6utHres","createdAt":"1730837163117","lastLoginAt":"1731548994242","passwordHash":"fakeHash:salt=fakeSalt2mk9sn6GSIy1LCWk1wfE:password=246890357Asefthuk","salt":"fakeSalt2mk9sn6GSIy1LCWk1wfE","passwordUpdatedAt":1733634018991,"providerUserInfo":[{"providerId":"password","email":"main.activity@test.com","federatedId":"main.activity@test.com","rawId":"main.activity@test.com"}],"validSince":"1733634018","email":"main.activity@test.com","emailVerified":false,"disabled":false}]}